[
  {
    "id": 1,
    "question": "<b>この<ruby>賞金<rp>（</rp><rt>しょうきん</rt><rp>）</rp></ruby>は<ruby>何<rp>（</rp><rt>なん</rt><rp>）</rp></ruby>（　）お<ruby>使<rp>（</rp><rt>つか</rt><rp>）</rp></ruby>いになるつもりですか。</b>",
    "options": [
      "も",
      "に"
    ],
    "correctAnswer": 1
  },
  {
    "id": 2,
    "question": "<b><ruby>先生<rp>（</rp><rt>せんせい</rt><rp>）</rp></ruby>の<ruby>予定<rp>（</rp><rt>よてい</rt><rp>）</rp></ruby>は<ruby>受付<rp>（</rp><rt>うけつけ</rt><rp>）</rp></ruby>に（　）ください。</b>",
    "options": [
      "お聞きになって",
      "伺って"
    ],
    "correctAnswer": 0
  },
  {
    "id": 3,
    "question": "<b>Album</b>",
    "options": [
      "アルバム",
      "そうべつかい",
      "うかがいます",
      "おります"
    ],
    "correctAnswer": 0
  },
  {
    "id": 4,
    "question": "<b>A：これは　なんですか。<p>B：（　）は　ごしゅっせきくださいましてです。</p></b>",
    "options": [
      "それ",
      "これ",
      "あれ",
      "どれ"
    ],
    "correctAnswer": 1
  },
  {
    "id": 5,
    "question": "<b>グプタさんは<ruby>刺身<rp>（</rp><rt>さしみ</rt><rp>）</rp></ruby>を（　）。</b>",
    "options": [
      "召し上がりません",
      "いただきません"
    ],
    "correctAnswer": 0
  },
  {
    "id": 6,
    "question": "<b>賞金</b>",
    "options": [
      "しょうきん",
      "わたくし",
      "さらいしゅう",
      "とります"
    ],
    "correctAnswer": 0
  },
  {
    "id": 7,
    "question": "<b>ガイド</b>",
    "options": [
      "Người hướng dẫn, hướng dẫn viên du lịch",
      "Kính thư (từ kết thúc của bức thư)",
      "Nghe, hỏi (từ khiêm tốn của ききます)",
      "Kính gửi (từ đầu thư)"
    ],
    "correctAnswer": 0
  },
  {
    "id": 8,
    "question": "<b>ぞんじます</b>",
    "options": [
      "Biết (từ khiêm tốn của しっています)",
      "Năm sau nữa",
      "Kính thư (từ kết thúc của bức thư)",
      "Tôi nói vài lời có được không?"
    ],
    "correctAnswer": 0
  },
  {
    "id": 9,
    "question": "<b>A：こうがいは　どこですか。<p>B：（　）です。</p></b>",
    "options": [
      "ここ",
      "そこ",
      "あそこ",
      "どこ"
    ],
    "correctAnswer": 0
  },
  {
    "id": 10,
    "question": "<b><ruby>初<rp>（</rp><rt>はじ</rt><rp>）</rp></ruby>めまして。（　）はミラーと<ruby>申<rp>（</rp><rt>もう</rt><rp>）</rp></ruby>します。</b>",
    "options": [
      "わたくし",
      "あなた"
    ],
    "correctAnswer": 0
  },
  {
    "id": 11,
    "question": "<b>この<ruby>間<rp>（</rp><rt>あいだ</rt><rp>）</rp></ruby>、<ruby>社長<rp>（</rp><rt>しゃちょう</rt><rp>）</rp></ruby>に（　）。</b>",
    "options": [
      "お目にかかりました",
      "ご覧になりました"
    ],
    "correctAnswer": 0
  },
  {
    "id": 12,
    "question": "<b>かないます</b>",
    "options": [
      "Trở thành hiện thực",
      "Anh (chị) có khỏe không ạ?",
      "Căng thẳng, lo lắng",
      "Tiệc chia tay"
    ],
    "correctAnswer": 0
  },
  {
    "id": 13,
    "question": "<b>きりん</b>",
    "options": [
      "Hươu cao cổ",
      "Trở thành hiện thực",
      "Tôi (khiêm tốn của わたし)",
      "Kính thư (từ kết thúc của bức thư)"
    ],
    "correctAnswer": 0
  },
  {
    "id": 14,
    "question": "<b>A：ぞうは　どちらですか。<p>B：（　）です。</p></b>",
    "options": [
      "こちら",
      "そちら",
      "あちら",
      "どちら"
    ],
    "correctAnswer": 0
  },
  {
    "id": 15,
    "question": "<b>こうがい</b>",
    "options": [
      "Ngoại ô, ngoại thành",
      "Ăn, uống, nhận (từ khiêm tốn của 食べます、のみます、もらいます)",
      "Địa danh của Đức",
      "Tôi nói vài lời có được không?"
    ],
    "correctAnswer": 0
  },
  {
    "id": 16,
    "question": "<b>Bảo tàng Edo Tokyo</b>",
    "options": [
      "えどとうきょうはくぶつかん",
      "そうべつかい",
      "はいけんします",
      "いただきます"
    ],
    "correctAnswer": 0
  },
  {
    "id": 17,
    "question": "<b>Có (kính ngữ của あります、います)</b>",
    "options": [
      "ございます",
      "おげんきでいらっしゃいますか",
      "おります",
      "もうします"
    ],
    "correctAnswer": 0
  },
  {
    "id": 18,
    "question": "<b>わたくしが<ruby>旅行<rp>（</rp><rt>りょこう</rt><rp>）</rp></ruby>について（　）。</b>",
    "options": [
      "説明されます",
      "ご説明します"
    ],
    "correctAnswer": 1
  },
  {
    "id": 19,
    "question": "<b>A：かないますは　どこですか。<p>B：（　）です。</p></b>",
    "options": [
      "ここ",
      "そこ",
      "あそこ",
      "どこ"
    ],
    "correctAnswer": 0
  },
  {
    "id": 20,
    "question": "<b>Là (cách nói lịch sự của です)</b>",
    "options": [
      "～でございます",
      "ころ",
      "アルバム",
      "けいぐ"
    ],
    "correctAnswer": 0
  },
  {
    "id": 21,
    "question": "<b>Thu</b>",
    "options": [
      "とります",
      "かないます",
      "いただきます",
      "では／それでは"
    ],
    "correctAnswer": 0
  },
  {
    "id": 22,
    "question": "<b>Kính thư (từ kết thúc của bức thư)</b>",
    "options": [
      "けいぐ",
      "ごしゅっせきくださいまして",
      "ころ",
      "いたします"
    ],
    "correctAnswer": 0
  },
  {
    "id": 23,
    "question": "<b><ruby>父<rp>（</rp><rt>ちち</rt><rp>）</rp></ruby>は<ruby>再来週<rp>（</rp><rt>さらいしゅう</rt><rp>）</rp></ruby><ruby>日本<rp>（</rp><rt>にほん</rt><rp>）</rp></ruby>へ（　）。<p></p></b>",
    "options": [
      "参ります",
      "来られます"
    ],
    "correctAnswer": 0
  },
  {
    "id": 24,
    "question": "<b>A：みなさまは　どちらですか。<p>B：（　）です。</p></b>",
    "options": [
      "こちら",
      "そちら",
      "あちら",
      "どちら"
    ],
    "correctAnswer": 0
  },
  {
    "id": 25,
    "question": "<b><ruby>先生<rp>（</rp><rt>せんせい</rt><rp>）</rp></ruby>は<ruby>何<rp>（</rp><rt>なん</rt><rp>）</rp></ruby>と（　）か。</b>",
    "options": [
      "おっしゃいました",
      "申しました"
    ],
    "correctAnswer": 0
  }
]