[
  {
    "id": 1,
    "question": "<b>Thu</b>",
    "options": [
      "とります",
      "いただきます",
      "うかがいます",
      "おいそがしいところ"
    ],
    "correctAnswer": 0
  },
  {
    "id": 2,
    "question": "<b>ごしんせつ</b>",
    "options": [
      "Chu đáo, cẩn thận (dùng cho người khác)",
      "Tôi (khiêm tốn của わたし)",
      "Tự nhiên, thiên nhiên",
      "Voi"
    ],
    "correctAnswer": 0
  },
  {
    "id": 3,
    "question": "<b><ruby>父<rp>（</rp><rt>ちち</rt><rp>）</rp></ruby>は<ruby>再来週<rp>（</rp><rt>さらいしゅう</rt><rp>）</rp></ruby><ruby>日本<rp>（</rp><rt>にほん</rt><rp>）</rp></ruby>へ（　）。<p></p></b>",
    "options": [
      "参ります",
      "来られます"
    ],
    "correctAnswer": 0
  },
  {
    "id": 4,
    "question": "<b>きれいな<ruby>桜<rp>（</rp><rt>さくら</rt><rp>）</rp></ruby>の<ruby>花<rp>（</rp><rt>はな</rt><rp>）</rp></ruby>をビデオ（　）<ruby>撮<rp>（</rp><rt>と</rt><rp>）</rp></ruby>って、<ruby>国<rp>（</rp><rt>くに</rt><rp>）</rp></ruby>の<ruby>家族<rp>（</rp><rt>かぞく</rt><rp>）</rp></ruby>（　）<ruby>見<rp>（</rp><rt>み</rt><rp>）</rp></ruby>せたいと<ruby>思<rp>（</rp><rt>おも</rt><rp>）</rp></ruby>います。</b>",
    "options": [
      "に、　に",
      "に、　が"
    ],
    "correctAnswer": 0
  },
  {
    "id": 5,
    "question": "<b>ございます</b>",
    "options": [
      "Có (kính ngữ của あります、います)",
      "Nghe, hỏi (từ khiêm tốn của ききます)",
      "Người hướng dẫn, hướng dẫn viên du lịch",
      "Gặp (từ khiêm tốn của)"
    ],
    "correctAnswer": 0
  },
  {
    "id": 6,
    "question": "<b>A：ガイドは　どちらですか。<p>B：（　）です。</p></b>",
    "options": [
      "こちら",
      "そちら",
      "あちら",
      "どちら"
    ],
    "correctAnswer": 0
  },
  {
    "id": 7,
    "question": "<b>Làm phiền</b>",
    "options": [
      "めいわくをかけます",
      "いたします",
      "かんしゃします",
      "しぜん"
    ],
    "correctAnswer": 0
  },
  {
    "id": 8,
    "question": "<b>お<ruby>名前<rp>（</rp><rt>なまえ</rt><rp>）</rp></ruby>は<ruby>何<rp>（</rp><rt>なん</rt><rp>）</rp></ruby>（　）おっしゃいますか。</b>",
    "options": [
      "と",
      "を"
    ],
    "correctAnswer": 0
  },
  {
    "id": 9,
    "question": "<b>A：ガイドは　どこですか。<p>B：（　）です。</p></b>",
    "options": [
      "ここ",
      "そこ",
      "あそこ",
      "どこ"
    ],
    "correctAnswer": 2
  },
  {
    "id": 10,
    "question": "<b>わたしは<ruby>毎晩<rp>（</rp><rt>まいばん</rt><rp>）</rp></ruby>３<ruby>時間<rp>（</rp><rt>じかん</rt><rp>）</rp></ruby>ぐらいテレビを（　）。</b>",
    "options": [
      "見ています",
      "ご覧になっています"
    ],
    "correctAnswer": 0
  },
  {
    "id": 11,
    "question": "<b>わたくしが<ruby>旅行<rp>（</rp><rt>りょこう</rt><rp>）</rp></ruby>について（　）。</b>",
    "options": [
      "説明されます",
      "ご説明します"
    ],
    "correctAnswer": 1
  },
  {
    "id": 12,
    "question": "<b>A：アルバムは　どちらですか。<p>B：（　）です。</p></b>",
    "options": [
      "こちら",
      "そちら",
      "あちら",
      "どちら"
    ],
    "correctAnswer": 2
  },
  {
    "id": 13,
    "question": "<b>ミュンヘン</b>",
    "options": [
      "Địa danh của Đức",
      "Là (cách nói lịch sự của です)",
      "Tháng sau nữa",
      "Biết (từ khiêm tốn của しっています)"
    ],
    "correctAnswer": 0
  },
  {
    "id": 14,
    "question": "<b>けいぐ</b>",
    "options": [
      "Kính thư (từ kết thúc của bức thư)",
      "Ăn, uống, nhận (từ khiêm tốn của 食べます、のみます、もらいます)",
      "Biết (từ khiêm tốn của しっています)",
      "Album"
    ],
    "correctAnswer": 0
  },
  {
    "id": 15,
    "question": "<b>おげんきでいらっしゃいますか</b>",
    "options": [
      "Anh (chị) có khỏe không ạ?",
      "Tiền thưởng",
      "Tuần sau nữa",
      "Khi, lúc"
    ],
    "correctAnswer": 0
  },
  {
    "id": 16,
    "question": "<b>(từ khiêm tốn của いいます)</b>",
    "options": [
      "もうします",
      "ごしんせつ",
      "とります",
      "いたします"
    ],
    "correctAnswer": 0
  },
  {
    "id": 17,
    "question": "<b><ruby>係<rp>（</rp><rt>かかり</rt><rp>）</rp></ruby>の<ruby>者<rp>（</rp><rt>もの</rt><rp>）</rp></ruby>は（　）<ruby>席<rp>（</rp><rt>せき</rt><rp>）</rp></ruby>を<ruby>外<rp>（</rp><rt>はず</rt><rp>）</rp></ruby>しております。</b>",
    "options": [
      "たった今",
      "ただ今"
    ],
    "correctAnswer": 1
  },
  {
    "id": 18,
    "question": "<b>しょうきん</b>",
    "options": [
      "Tiền thưởng",
      "Làm (từ khiêm tốn します)",
      "Năm sau nữa",
      "Quí vị"
    ],
    "correctAnswer": 0
  },
  {
    "id": 19,
    "question": "<b><ruby>先生<rp>（</rp><rt>せんせい</rt><rp>）</rp></ruby>の<ruby>予定<rp>（</rp><rt>よてい</rt><rp>）</rp></ruby>は<ruby>受付<rp>（</rp><rt>うけつけ</rt><rp>）</rp></ruby>に（　）ください。</b>",
    "options": [
      "お聞きになって",
      "伺って"
    ],
    "correctAnswer": 0
  },
  {
    "id": 20,
    "question": "<b>頂きます</b>",
    "options": [
      "いただきます",
      "かんしゃします",
      "さらいねん",
      "しょうきん"
    ],
    "correctAnswer": 0
  },
  {
    "id": 21,
    "question": "<b>ミラーさんがスポーツ<ruby>大会<rp>（</rp><rt>たいかい</rt><rp>）</rp></ruby>（　）<ruby>優勝<rp>（</rp><rt>ゆうしょう</rt><rp>）</rp></ruby>したの（　）ご<ruby>存<rp>（</rp><rt>ぞん</rt><rp>）</rp></ruby>じですか。</b>",
    "options": [
      "で、を",
      "へ、を"
    ],
    "correctAnswer": 0
  },
  {
    "id": 22,
    "question": "<b>アルバム</b>",
    "options": [
      "Album",
      "Tiệc chia tay",
      "Hươu cao cổ",
      "Chu đáo, cẩn thận (dùng cho người khác)"
    ],
    "correctAnswer": 0
  },
  {
    "id": 23,
    "question": "<b>A：ごしんせつは　どこですか。<p>B：（　）です。</p></b>",
    "options": [
      "ここ",
      "そこ",
      "あそこ",
      "どこ"
    ],
    "correctAnswer": 1
  },
  {
    "id": 24,
    "question": "<b>A：これは　なんですか。<p>B：（　）は　ほうそうしますです。</p></b>",
    "options": [
      "それ",
      "これ",
      "あれ",
      "どれ"
    ],
    "correctAnswer": 1
  }
]