[
  {
    "id": "toThink",
    "kanji": "思います",
    "hiragana": "おもいます",
    "en": "to think",
    "vi": "nghĩ, nghĩ rằng, cho rằng",
    "type": "verb",
    "explanation": {
      "content": [
        "Động từ nhóm I",
        "Ví dụ: そう思います。 (Tôi nghĩ vậy.)"
      ]
    }
  },
  {
    "id": "toSay",
    "kanji": "言います",
    "hiragana": "いいます",
    "en": "to say",
    "vi": "nói",
    "type": "verb",
    "explanation": {
      "content": [
        "Động từ nhóm I",
        "Ví dụ: ありがとうと言います。 (Nói cảm ơn.)"
      ]
    }
  },
  {
    "id": "toBeUseful",
    "kanji": "役に立ちます",
    "hiragana": "やくにたちます",
    "en": "to be useful",
    "vi": "có ích, có lợi",
    "type": "verb",
    "explanation": {
      "content": [
        "Động từ nhóm I",
        "Ví dụ: この本は役に立ちます。 (Cuốn sách này có ích.)"
      ]
    }
  },
  {
    "id": "convenient",
    "kanji": "便利",
    "hiragana": "べんり",
    "en": "convenient",
    "vi": "tiện lợi",
    "type": "adjective",
    "explanation": {
      "content": [
        "Tính từ な (な-adjective)",
        "Ví dụ: 便利な道具です。 (Dụng cụ tiện lợi.)"
      ]
    }
  },
  {
    "id": "inconvenient",
    "kanji": "不便",
    "hiragana": "ふべん",
    "en": "inconvenient",
    "vi": "không tiện, bất tiện",
    "type": "adjective",
    "explanation": {
      "content": [
        "Tính từ な (な-adjective)",
        "Ví dụ: 不便な場所です。 (Nơi bất tiện.)"
      ]
    }
  },
  {
    "id": "same",
    "kanji": "同じ",
    "hiragana": "おなじ",
    "en": "same",
    "vi": "giống, giống nhau, chung",
    "type": "adjective",
    "explanation": {
      "content": [
        "Tính từ な (な-adjective)",
        "Ví dụ: 同じ本です。 (Cùng một cuốn sách.)"
      ]
    }
  },
  {
    "id": "trainingTrip",
    "kanji": "研修旅行",
    "hiragana": "けんしゅうりょこう",
    "en": "training trip",
    "vi": "chuyến du lịch thực tập",
    "type": "noun",
    "explanation": {
      "content": [
        "Danh từ chỉ chuyến du lịch thực tập",
        "Ví dụ: 研修旅行へ行きます。 (Đi du lịch thực tập.)"
      ]
    }
  },
  {
    "id": "opinion",
    "kanji": "意見",
    "hiragana": "いけん",
    "en": "opinion",
    "vi": "ý kiến",
    "type": "noun",
    "explanation": {
      "content": [
        "Danh từ chỉ ý kiến",
        "Ví dụ: 意見を言います。 (Nói ý kiến.)"
      ]
    }
  },
  {
    "id": "meeting",
    "kanji": "会議",
    "hiragana": "かいぎ",
    "en": "meeting",
    "vi": "cuộc họp",
    "type": "noun",
    "explanation": {
      "content": [
        "Danh từ chỉ cuộc họp",
        "Ví dụ: 会議をします。 (Tổ chức cuộc họp.)"
      ]
    }
  },
  {
    "id": "question",
    "kanji": "質問",
    "hiragana": "しつもん",
    "en": "question",
    "vi": "câu hỏi",
    "type": "noun",
    "explanation": {
      "content": [
        "Danh từ chỉ câu hỏi",
        "Ví dụ: 質問をします。 (Đặt câu hỏi.)"
      ]
    }
  },
  {
    "id": "technology",
    "kanji": "技術",
    "hiragana": "ぎじゅつ",
    "en": "technology",
    "vi": "kỹ thuật",
    "type": "noun",
    "explanation": {
      "content": [
        "Danh từ chỉ kỹ thuật",
        "Ví dụ: 技術を勉強します。 (Học kỹ thuật.)"
      ]
    }
  },
  {
    "id": "traffic",
    "kanji": "交通",
    "hiragana": "こうつう",
    "en": "traffic",
    "vi": "giao thông",
    "type": "noun",
    "explanation": {
      "content": [
        "Danh từ chỉ giao thông",
        "Ví dụ: 交通が便利です。 (Giao thông tiện lợi.)"
      ]
    }
  },
  {
    "id": "recently",
    "kanji": "最近",
    "hiragana": "さいきん",
    "en": "recently",
    "vi": "gần đây",
    "type": "adverb",
    "explanation": {
      "content": [
        "Phó từ chỉ thời gian",
        "Ví dụ: 最近、忙しいです。 (Gần đây bận.)"
      ]
    }
  },
  {
    "id": "probably",
    "kanji": "たぶん",
    "hiragana": "たぶん",
    "en": "probably",
    "vi": "có lẽ",
    "type": "adverb",
    "explanation": {
      "content": [
        "Phó từ chỉ khả năng",
        "Ví dụ: たぶん来ます。 (Có lẽ sẽ đến.)"
      ]
    }
  },
  {
    "id": "surely",
    "kanji": "きっと",
    "hiragana": "きっと",
    "en": "surely",
    "vi": "chắc chắn",
    "type": "adverb",
    "explanation": {
      "content": [
        "Phó từ chỉ khả năng",
        "Ví dụ: きっと来ます。 (Chắc chắn sẽ đến.)"
      ]
    }
  },
  {
    "id": "really",
    "kanji": "本当に",
    "hiragana": "ほんとうに",
    "en": "really",
    "vi": "thật là, quả thật, đúng là",
    "type": "adverb",
    "explanation": {
      "content": [
        "Phó từ chỉ mức độ",
        "Ví dụ: 本当にありがとうございます。 (Thật là cảm ơn.)"
      ]
    }
  },
  {
    "id": "notThatMuch",
    "kanji": "そんなに",
    "hiragana": "そんなに",
    "en": "not that much",
    "vi": "không đến mức ~ như thế (đi với dạng phủ định)",
    "type": "adverb",
    "explanation": {
      "content": [
        "Phó từ phủ định",
        "Ví dụ: そんなに難しくありません。 (Không khó đến mức như thế.)"
      ]
    }
  },
  {
    "id": "about",
    "kanji": "～について",
    "hiragana": "～について",
    "en": "about",
    "vi": "về",
    "type": "other",
    "explanation": {
      "content": [
        "Trợ từ chỉ chủ đề",
        "Ví dụ: 日本について話します。 (Nói về Nhật Bản.)"
      ]
    }
  },
  {
    "id": "other",
    "kanji": "他の～",
    "hiragana": "ほかの～",
    "en": "other",
    "vi": "~ khác",
    "type": "other",
    "explanation": {
      "content": [
        "Từ chỉ định",
        "Ví dụ: 他の本 (Cuốn sách khác)"
      ]
    }
  },
  {
    "id": "but",
    "kanji": "けれども",
    "hiragana": "けれども",
    "en": "but",
    "vi": "nhưng mà",
    "type": "other",
    "explanation": {
      "content": [
        "Từ nối",
        "Ví dụ: 行きたいけれども、時間がありません。 (Muốn đi nhưng mà không có thời gian.)"
      ]
    }
  },
  {
    "id": "japanIsAdvanced",
    "kanji": "「日本は」技術が進んでいます",
    "hiragana": "「にほんは」ぎじゅつがすすんでいます",
    "en": "Japan is advanced in technology",
    "vi": "[Nhật Bản] tiên tiến về kỹ thuật. [Ở Nhật Bản] kỹ thuật phát triển (cao)",
    "type": "other",
    "explanation": {
      "content": [
        "Câu nói về sự phát triển",
        "Ví dụ: 「日本は」技術が進んでいます。 (Nhật Bản tiên tiến về kỹ thuật.)"
      ]
    }
  },
  {
    "id": "toWin",
    "kanji": "勝ちます",
    "hiragana": "かちます",
    "en": "to win",
    "vi": "thắng, chiến thắng",
    "type": "verb",
    "explanation": {
      "content": [
        "Động từ nhóm I",
        "Ví dụ: 試合に勝ちます。 (Thắng trận đấu.)"
      ]
    }
  },
  {
    "id": "toBeEnough",
    "kanji": "足ります",
    "hiragana": "たります",
    "en": "to be enough",
    "vi": "đủ, đầy đủ",
    "type": "verb",
    "explanation": {
      "content": [
        "Động từ nhóm I",
        "Ví dụ: お金が足ります。 (Tiền đủ.)"
      ]
    }
  },
  {
    "id": "toLose",
    "kanji": "負けます",
    "hiragana": "まけます",
    "en": "to lose",
    "vi": "thua, thất bại",
    "type": "verb",
    "explanation": {
      "content": [
        "Động từ nhóm II",
        "Ví dụ: 試合に負けます。 (Thua trận đấu.)"
      ]
    }
  },
  {
    "id": "toAsk",
    "kanji": "質問（します、する、して）",
    "hiragana": "しつもん（します、する、して）",
    "en": "to ask",
    "vi": "câu hỏi, hỏi",
    "type": "verb",
    "explanation": {
      "content": [
        "Động từ nhóm III (する)",
        "Ví dụ: 質問をします。 (Đặt câu hỏi.)"
      ]
    }
  },
  {
    "id": "wasteful",
    "kanji": "無駄",
    "hiragana": "むだ",
    "en": "wasteful",
    "vi": "phí, lãng phí",
    "type": "adjective",
    "explanation": {
      "content": [
        "Tính từ な (な-adjective)",
        "Ví dụ: 無駄な時間です。 (Thời gian lãng phí.)"
      ]
    }
  },
  {
    "id": "amazing",
    "kanji": "すごい",
    "hiragana": "すごい",
    "en": "amazing",
    "vi": "tuyệt vời, khủng khiếp, kỳ diệu",
    "type": "adjective",
    "explanation": {
      "content": [
        "Tính từ i (い-adjective)",
        "Ví dụ: すごい人です。 (Người tuyệt vời.)"
      ]
    }
  },
  {
    "id": "primeMinister",
    "kanji": "首相",
    "hiragana": "しゅしょう",
    "en": "prime minister",
    "vi": "thủ tướng",
    "type": "noun",
    "explanation": {
      "content": [
        "Danh từ chỉ chức vụ",
        "Ví dụ: 首相に会います。 (Gặp thủ tướng.)"
      ]
    }
  },
  {
    "id": "president",
    "kanji": "大統領",
    "hiragana": "だいとうりょう",
    "en": "president",
    "vi": "tổng thống",
    "type": "noun",
    "explanation": {
      "content": [
        "Danh từ chỉ chức vụ",
        "Ví dụ: 大統領に会います。 (Gặp tổng thống.)"
      ]
    }
  },
  {
    "id": "politics",
    "kanji": "政治",
    "hiragana": "せいじ",
    "en": "politics",
    "vi": "chính trị",
    "type": "noun",
    "explanation": {
      "content": [
        "Danh từ chỉ chính trị",
        "Ví dụ: 政治を勉強します。 (Học chính trị.)"
      ]
    }
  },
  {
    "id": "news",
    "kanji": "ニュース",
    "hiragana": "ニュース",
    "en": "news",
    "vi": "bản tin, tin tức",
    "type": "noun",
    "explanation": {
      "content": [
        "Danh từ chỉ tin tức (từ mượn)",
        "Ví dụ: ニュースを見ます。 (Xem tin tức.)"
      ]
    }
  },
  {
    "id": "speech",
    "kanji": "スピーチ",
    "hiragana": "スピーチ",
    "en": "speech",
    "vi": "bài phát biểu, bài nói chuyện",
    "type": "noun",
    "explanation": {
      "content": [
        "Danh từ chỉ bài phát biểu (từ mượn)",
        "Ví dụ: スピーチをします。 (Phát biểu.)"
      ]
    }
  },
  {
    "id": "toGiveSpeech",
    "kanji": "スピーチ「～をします」",
    "hiragana": "スピーチ「～をします」",
    "en": "to give a speech",
    "vi": "[bài phát biểu, bài nói chuyện]",
    "type": "verb",
    "explanation": {
      "content": [
        "Động từ nhóm III (する)",
        "Ví dụ: スピーチをします。 (Phát biểu.)"
      ]
    }
  },
  {
    "id": "game",
    "kanji": "試合",
    "hiragana": "しあい",
    "en": "game",
    "vi": "trận đấu, trò chơi",
    "type": "noun",
    "explanation": {
      "content": [
        "Danh từ chỉ trận đấu",
        "Ví dụ: 試合を見ます。 (Xem trận đấu.)"
      ]
    }
  },
  {
    "id": "partTimeJob",
    "kanji": "アルバイト",
    "hiragana": "アルバイト",
    "en": "part-time job",
    "vi": "làm thêm, làm partime",
    "type": "noun",
    "explanation": {
      "content": [
        "Danh từ chỉ việc làm thêm (từ mượn)",
        "Ví dụ: アルバイトをします。 (Làm thêm.)"
      ]
    }
  },
  {
    "id": "toDoPartTimeJob",
    "kanji": "アルバイト「～をします」",
    "hiragana": "アルバイト「～をします」",
    "en": "to do a part-time job",
    "vi": "[làm thêm, làm partime]",
    "type": "verb",
    "explanation": {
      "content": [
        "Động từ nhóm III (する)",
        "Ví dụ: アルバイトをします。 (Làm thêm.)"
      ]
    }
  },
  {
    "id": "story",
    "kanji": "お話",
    "hiragana": "おはなし",
    "en": "story",
    "vi": "câu chuyện",
    "type": "noun",
    "explanation": {
      "content": [
        "Danh từ chỉ câu chuyện, có tiền tố お (lịch sự)",
        "Ví dụ: お話をします。 (Kể chuyện.)"
      ]
    }
  },
  {
    "id": "toTellStory",
    "kanji": "お話「～をします」",
    "hiragana": "おはなし「～をします」",
    "en": "to tell a story",
    "vi": "[câu chuyện]",
    "type": "verb",
    "explanation": {
      "content": [
        "Động từ nhóm III (する)",
        "Ví dụ: お話をします。 (Kể chuyện.)"
      ]
    }
  },
  {
    "id": "humor",
    "kanji": "ユーモア",
    "hiragana": "ユーモア",
    "en": "humor",
    "vi": "sự hài hước, hóm hỉnh",
    "type": "noun",
    "explanation": {
      "content": [
        "Danh từ chỉ sự hài hước (từ mượn)",
        "Ví dụ: ユーモアがあります。 (Có sự hài hước.)"
      ]
    }
  },
  {
    "id": "design",
    "kanji": "デザイン",
    "hiragana": "デザイン",
    "en": "design",
    "vi": "mẫu thiết kế",
    "type": "noun",
    "explanation": {
      "content": [
        "Danh từ chỉ mẫu thiết kế (từ mượn)",
        "Ví dụ: デザインがいいです。 (Mẫu thiết kế đẹp.)"
      ]
    }
  },
  {
    "id": "rushHour",
    "kanji": "ラッシュ（アワー）",
    "hiragana": "ラッシュ（アワー）",
    "en": "rush hour",
    "vi": "giờ cao điểm",
    "type": "noun",
    "explanation": {
      "content": [
        "Danh từ chỉ giờ cao điểm (từ mượn)",
        "Ví dụ: ラッシュアワーです。 (Giờ cao điểm.)"
      ]
    }
  },
  {
    "id": "noWay",
    "kanji": "しかたがありません",
    "hiragana": "しかたがありません",
    "en": "no way",
    "vi": "không còn cách nào khác",
    "type": "other",
    "explanation": {
      "content": [
        "Câu nói về sự bất lực",
        "Ví dụ: しかたがありません。 (Không còn cách nào khác.)"
      ]
    }
  },
  {
    "id": "wouldYouLikeToDrink",
    "kanji": "～でも飲みませんか",
    "hiragana": "～でものみませんか",
    "en": "would you like to drink",
    "vi": "bạn có uống… không?",
    "type": "other",
    "explanation": {
      "content": [
        "Câu mời lịch sự",
        "Ví dụ: コーヒーでも飲みませんか。 (Bạn có uống cà phê không?)"
      ]
    }
  },
  {
    "id": "mustSee",
    "kanji": "ぜひ見ないと……",
    "hiragana": "ぜひみないと……",
    "en": "must see",
    "vi": "nhất định tôi phải xem…",
    "type": "other",
    "explanation": {
      "content": [
        "Câu biểu thị ý định",
        "Ví dụ: ぜひ見ないと…… (Nhất định tôi phải xem…)"
      ]
    }
  },
  {
    "id": "ofCourse",
    "kanji": "もちろん",
    "hiragana": "もちろん",
    "en": "of course",
    "vi": "đương nhiên, dĩ nhiên",
    "type": "adverb",
    "explanation": {
      "content": [
        "Phó từ chỉ sự hiển nhiên",
        "Ví dụ: もちろん行きます。 (Đương nhiên sẽ đi.)"
      ]
    }
  },
  {
    "id": "kangaroo",
    "kanji": "カンガルー",
    "hiragana": "カンガルー",
    "en": "kangaroo",
    "vi": "con kangaroo",
    "type": "noun",
    "explanation": {
      "content": [
        "Danh từ chỉ động vật (từ mượn)",
        "Ví dụ: カンガルーがいます。 (Có kangaroo.)"
      ]
    }
  },
  {
    "id": "captainCook",
    "kanji": "キャプテン・クック",
    "hiragana": "キャプテン・クック",
    "en": "Captain Cook",
    "vi": "thuyền trưởng James Cook",
    "type": "noun",
    "explanation": {
      "content": [
        "Tên người",
        "Ví dụ: キャプテン・クックです。 (Là thuyền trưởng James Cook.)"
      ]
    }
  }
]
